i4u/__init__.py
i4u/classes.py
i4u/doc_req.py
i4u-0.0.7.dist-info/LICENSE
i4u-0.0.7.dist-info/METADATA
i4u-0.0.7.dist-info/WHEEL
i4u-0.0.7.dist-info/top_level.txt
i4u-0.0.7.dist-info/RECORD
