Metadata-Version: 2.1
Name: i4u
Version: 0.0.7
Summary: Python package to interact with Invoice4U API
Home-page: https://github.com/ofersadan85/i4u
Author: Ofer Sadan
Author-email: ofersadan85@gmail.com
License: MIT License
Platform: UNKNOWN
Classifier: License :: OSI Approved :: MIT License
Classifier: Programming Language :: Python :: 3
Classifier: Programming Language :: Python :: 3.6
Classifier: Programming Language :: Python :: 3.7
Classifier: Programming Language :: Python :: 3.8
Classifier: Programming Language :: Python :: 3.9
Classifier: Programming Language :: Python :: 3.10
License-File: LICENSE
Requires-Dist: requests (>=2.25.1)
Requires-Dist: zeep (>=4.0.0)
Requires-Dist: dataclasses ; python_version < "3.7"
